azul_api/center_taking_request.py
azul_api/factory_taking_request.py
azul_api/game_controller.py
azul_api/main.py
azul_api-1.0.3.dist-info/licenses/LICENSE
azul_api-1.0.3.dist-info/METADATA
azul_api-1.0.3.dist-info/WHEEL
azul_api-1.0.3.dist-info/top_level.txt
azul_api-1.0.3.dist-info/RECORD
