Metadata-Version: 2.4
Name: azul_api
Version: 1.0.3
Summary: An API for Azul board game
Author-email: Evaldas Visockas <developersediary@gmail.com>
License: GPL-3.0-or-later
Project-URL: Repository, https://github.com/AzulImplementation/AzulApi
Requires-Python: >=3.12
License-File: LICENSE
Requires-Dist: azul-game-engine>=1.0.2
Requires-Dist: flask>=3.1.1
Requires-Dist: flasgger>=0.9.7.1
Dynamic: license-file
